{
  "buttonCommands": {
    "support": {
      "application_label": "랭크 신청 및 구매",
      "application_description": "랭크를 신청하시거나 구매하시기 위해선 이 티켓을 열어주세요!",
      "report_label": "플레이어 및 버그 신고",
      "report_description": "티켓을 열어 버그 혹은 플레이어를 신고해보세요!",
      "support_label": "문의",
      "support_description": "문의하실 것들이 있으시다면 티켓을 열어 말씀해주세요!",
      "placeholder": "여기에서 티켓 종류를 골라주세요!",
      "embed_description": "<:checkmenu:948811814655893515> __**도움이 필요하시거나 문의하고 싶으신 것이 있나요??**__\n> <:close:948394548588064838> 편하게 티켓을 만들어주세요! 저희 관리진은 도움이 될 수 있는 대로 도와드리겠습니다!\n> <:ban_menu:948463237991657502> 장난식 티켓은 처벌로 이어질 수 있습니다!\n\n<:checkmenu:948811814655893515> __**서버에서 버그를 찾으셨나요? 규칙을 위반하는 유저를 발견하셨나요?**__\n> <:close:948394548588064838> 신고 티켓을 만들어 저희에게 알려주세요! 가능한 한 빨리 처리하겠습니다.\n> <:report_menu:948184891009417256> 채팅 신고는 `/chatlog` 또는 `/cl` 커맨드를 이용해주세요!\n> <:report_menu:948184891009417256> 신고를 위해서는 상황을 녹화한 동영상이 필수입니다!\n\n<:checkmenu:948811814655893515> __**랭크를 사거나 지원하고 싶으신가요?**__ \n> <:close:948394548588064838> 그렇다면 이 신청 티켓을 열어주세요!\n> <:claim:948453007136272414> `관리진` 랭크는 신청이 불가합니다. 추후 공지에서 뽑을 수도 있어요!"
    },
    "appeal": {
      "ban_label": "기타 밴 항소",
      "ban_description": "자신의 밴을 항소하고 싶으시면 이 티켓을 열어주세요!",
      "autoclick_label": "오토클릭 밴 항소",
      "autoclick_description": "오토클릭 밴을 항소하고 싶으시면 이 티켓을 열어주세요!",
      "mute_label": "뮤트 항소",
      "mute_description": "자신의 뮤트에 대하여 항소하고 싶으시면 이 티켓을 열어주세요!",
      "placeholder": "여기에서 티켓 종류를 골라주세요!",
      "embed_description": "<:checkmenu:948811814655893515>  __**오토클릭으로 밴을 당해서 항소하고 싶으신가요?**__\n> <:close:948394548588064838> 오토클릭 밴 항소 티켓을 만들어보세요! 저희 관리진들이 최선을 다해 도와드리겠습니다.\n> <:ban_menu:948463237991657502> 장난식 티켓은 처벌로 이어집니다!\n> <:report_menu:948184891009417256> 오토클릭으로 인한 밴은 무죄를 입증하려면 손캠이 필요하니, 마음의 준비를 해놓으세요!!\n\n<:checkmenu:948811814655893515> __**서버에서 밴을 당했고, 다시 서버에 접속하고 싶으시다고요?**__\n> <:close:948394548588064838> 밴 항소 티켓을 만들어서 항소해보세요! 어쩌면 밴을 풀 수 있을지도 모르죠!\n> <:report_menu:948184891009417256> 관리진들이 원활하게 도와드리기 위해서 항소 양식을 지켜주세요!\n\n<:checkmenu:948811814655893515> __**뮤트를 당했고 풀고 싶으시다고요?**__ \n> <:close:948394548588064838> 뮤트 항소 티켓을 만들어 억울함을 호소해보세요!\n> <:report_menu:948184891009417256> 저희는 채팅 기록을 가지고 있으니, 당시 상황을 최대한 잘 설명해주세요!"
    }
  },
  "selectMenuCommands": {
    "support": {
      "channelLimit": "**채널을 만들 수 없습니다! 기타 채팅 채널에서 관리진을 멘션해주세요!**",
      "channelExist": "**이미 티켓이 존재합니다!**",
      "support": {
        "ticketName": "문의",
        "ticketTopic": "{ticketOwner}님이 만드신 문의 티켓입니다! 문의하실 점들을 편하게 얘기해주세요!",
        "ticketContent": "**문의 티켓이 생성되었습니다!**\n",
       "embed_description": "<:support:948021689588002857> **서포트 티켓을 이용하시기 전에 확인해주세요!**\n\n\n> `•` 서포트 티켓은 **항소 티켓**이 아닙니다.\n> \n> `•` **관리자를 멘션**하지 마세요.\n> \n> `•` 관리진이 응답하기까지 최대 **3일**이 걸릴 수 있으며, 재촉하지 마세요."
      },
      "report": {
        "ticketName": "신고",
        "ticketTopic": "신고하시고 싶은 것이 있으시다면 자유롭게 적어주세요!",
        "ticketContent": "**신고 티켓이 생성되었습니다!**\n",
        "embed_description": "<:report_menu:948184891009417256> **신고 티켓을 이용하시기 전에 확인해주세요!**\n\n\n> `•` 채팅 신고는 `/chatlog` 혹은 `/cl` **커맨드**로만 가능합니다.\n> \n> `•` 모든 증거들은 **영상 녹화**이여야 하며, 스크린샷은 받지 않습니다.\n> \n> `•` **관리진을 멘션**하지 마세요.\n> \n> `•` 관리진이 응답하기까지 최대 **3일**이 걸릴 수 있으며, 재촉하지 마세요."
      },
      "application": {
        "ticketName": "신청",
        "ticketTopic": "{ticketOwner}님이 만드신 랭크 신청 티켓입니다! 어떤 랭크를 신청할 것인지 말씀해주세요!",
        "ticketContent": "**랭크 신청 티켓이 생성되었습니다!**\n",
        "embed_description": "<:unclaim:948452951498829824> **신청 티켓을 이용하시기 전에 확인해주세요!**\n\n\n> `•` 오직 **verified** 랭크만 신청 가능합니다.\n> \n> `•` 랭크 신청을 위해서 **핸드캠 가이드**를 따라주세요..\n> \n> `•` **관리진을 멘션**하지 마세요.\n> \n> `•` 관리진이 응답하기까지 최대 **3일**이 걸릴 수 있으며, 재촉하지 마세요."
      }
    },
    "appeal": {
      "channelLimit": "**채널을 만들 수 없습니다! 기타 채팅 채널에서 관리진을 멘션해주세요!**",
      "channelExist": "**이미 항소 티켓이 존재합니다!**",
      "autoclicker": {
        "ticketName": "오토클릭",
        "ticketTopic": "오토클릭 밴 항소 티켓입니다! 핸드캠 가이드를 꼼꼼히 읽어보세요!",
        "ticketContent": "**오토클릭 항소 티켓이 생성되었습니다!**\n",
        "embed_description": "<:appeal:948460468039745646> **오토클릭 밴에 대하여 항소하기 위해서 아래 양식을 채워주세요!**\n\n\n<:saved:948369755092426762> **__항소 양식__**\n\n> `•` 오토클릭을 사용하셨다는 걸 인정하십니까?\n> \n> `•`  우리가 귀하의 밴을 풀어줘야 하는 이유는 무엇입니까?\n\n\n<:report_menu:948184891009417256> ***관리진을 멘션하지 마세요***, *항소이 즉각 거부될 수 있습니다.*\n<:report_menu:948184891009417256> *양식을* ***제대로 채워주세요***, *아니면 관리진들이 도와드리기 어렵습니다.*\n<:report_menu:948184891009417256> *관리진이 응답하기까지 최대* ***3일**이 걸릴 수 있으며, 재촉하지 마세요.*"
      },
      "ban": {
        "ticketName": "밴",
        "ticketTopic": "자신이 언제 밴되었는지, 무슨 일이 일어났는지, 왜 언밴되어야 하는지 서술해주세요!",
        "ticketContent": "**밴 항소 티켓이 생성되었습니다!**\n",
        "embed_description": "<:appeal:948460468039745646> **자신의 밴에 대하여 항소하기 위해서 아래 양식을 채워주세요!**\n\n\n<:saved:948369755092426762> **__항소 양식__**\n\n> `•` 핵을 사용하셨다는 것을 인정하십니까?\n> \n> `•`  우리가 귀하의 밴을 풀어줘야 하는 이유는 무엇입니까?\n\n\n<:report_menu:948184891009417256> ***관리진을 멘션하지 마세요***, *항소이 즉각 거부될 수 있습니다.*\n<:report_menu:948184891009417256> *양식을* ***제대로 채워주세요***, *아니면 관리진들이 도와드리기 어렵습니다.*\n<:report_menu:948184891009417256> *관리진이 응답하기까지 최대* ***3일**이 걸릴 수 있으며, 재촉하지 마세요.*"
      },
      "mute": {
        "ticketName": "뮤트",
        "ticketTopic": "자신의 뮤트가 풀려야 하는 이유를 상세히 설명해주세요!",
        "ticketContent": "**뮤트 항소 티켓이 생성되었습니다!**\n",
        "embed_description": "<:appeal:948460468039745646> **자신의 뮤트에 대하여 항소하기 위해서 아래 양식을 채워주세요!**\n\n\n<:saved:948369755092426762> **__항소 양식__**\n\n> `•` 자신의 뮤트는 정당하다고 생각하십니까?\n> \n> `•`  정확히 무슨 일이 일어났습니까?\n> \n> `•`  우리가 귀하의 뮤트를 풀어줘야 하는 이유는 무엇입니까?\n\n\n<:report_menu:948184891009417256> ***관리진을 멘션하지 마세요***, *항소이 즉각 거부될 수 있습니다.*\n<:report_menu:948184891009417256> *양식을* ***제대로 채워주세요***, *아니면 관리진들이 도와드리기 어렵습니다.*\n<:report_menu:948184891009417256> *관리진이 응답하기까지 최대* ***3일**이 걸릴 수 있으며, 재촉하지 마세요.*"
      }
    }
  }
}
